rrlfe/__init__.py
rrlfe/__init__backup.py
rrlfe/compile_normalization.py
rrlfe/conf/config_apply.ini
rrlfe/conf/config_gen.ini
rrlfe/conftest.py
rrlfe/consolidate_pre_mcmc.py
rrlfe/covars.py
rrlfe/create_spec_realizations.py
rrlfe/error_propagation_and_mapping.py
rrlfe/final_corrxn.py
rrlfe/find_feh.py
rrlfe/high_level_application_accordion.py
rrlfe/high_level_generation_accordion.py
rrlfe/interpolate_spectra_masked_regions.py
rrlfe/make_high_res_feh_basis.py
rrlfe/manually_remove_points_spectra.py
rrlfe/norm_spec.py
rrlfe/normalize_simple.py
rrlfe/plot_utils.py
rrlfe/run_emcee.py
rrlfe/run_robo.py
rrlfe/scrape_ew_and_errew.py
rrlfe/sdss_spectra_cosmic_ray_removal.py
rrlfe/set_params.py
rrlfe/sift_manual_spectra.py
rrlfe/teff_retrieval.py
rrlfe/test.pdf
rrlfe/test_resids.pdf
rrlfe/test_src/bckgrnd_input.txt
rrlfe/test_synced.pdf
rrlfe/test_unsynced.pdf
rrlfe/tests/.coverage
rrlfe/tests/20230226_170843.log
rrlfe/tests/__init__.py
rrlfe/tests/test_compile_normalization.py
rrlfe/tests/test_create_spec_realizations.py
rrlfe/tests/test_init_fcns.py
rrlfe/tests/test_run_emcee.py
rrlfe/tests/test_run_robo.py
rrlfe/tests/test_scrape_ew_and_errew.py
rrlfe/tests/test_teff_retrieval.py
rrlfe/write_masks_for_no_ray_spectra.py
rrlfe-1.0.dist-info/LICENSE
rrlfe-1.0.dist-info/LICENSE.txt
rrlfe-1.0.dist-info/METADATA
rrlfe-1.0.dist-info/WHEEL
rrlfe-1.0.dist-info/RECORD
