Metadata-Version: 2.1
Name: rrlfe
Version: 1.0
Summary: For finding FeH from low-res survey spectra of RR Lyrae stars
Home-page: https://github.com/mwanakijiji/rrlfe
Author: Eckhart Spalding
Author-email: eckhart.spalding@sydney.edu.au
Requires-Python: >=3.8,<4.0
Classifier: Programming Language :: Python :: 3
Classifier: Programming Language :: Python :: 3.8
Classifier: Programming Language :: Python :: 3.9
Classifier: Programming Language :: Python :: 3.10
Classifier: Programming Language :: Python :: 3.11
Classifier: Programming Language :: Python :: 3.12
Project-URL: Repository, https://github.com/mwanakijiji/rrlfe
